imacropy/__init__.py
imacropy/console.py
imacropy/iconsole.py
imacropy/util.py
imacropy-0.3.1.data/scripts/macropy3
imacropy-0.3.1.dist-info/LICENSE.md
imacropy-0.3.1.dist-info/METADATA
imacropy-0.3.1.dist-info/WHEEL
imacropy-0.3.1.dist-info/top_level.txt
imacropy-0.3.1.dist-info/RECORD
