Metadata-Version: 2.1
Name: imacropy
Version: 0.3.1
Summary: Interactive MacroPy - IPython REPL, embeddable REPL, bootstrapper.
Home-page: https://github.com/Technologicat/imacropy
Author: Juha Jeronen
Author-email: juha.m.jeronen@gmail.com
License: BSD
Keywords: metaprogramming,syntactic-macros,macropy,console,repl
Platform: Linux
Classifier: Development Status :: 4 - Beta
Classifier: Environment :: Console
Classifier: Intended Audience :: Developers
Classifier: License :: OSI Approved :: BSD License
Classifier: Operating System :: POSIX :: Linux
Classifier: Programming Language :: Python
Classifier: Programming Language :: Python :: 3
Classifier: Programming Language :: Python :: 3.6
Classifier: Topic :: Software Development :: Libraries
Classifier: Topic :: Software Development :: Libraries :: Python Modules
Classifier: Framework :: IPython
Provides: imacropy
Requires-Dist: macropy3
